fake_number_id/__init__.py
fake_number_id/gsm_prefiks.py
fake_number_id/penyedia.py
fake_number_id-1.0.dist-info/METADATA
fake_number_id-1.0.dist-info/WHEEL
fake_number_id-1.0.dist-info/RECORD
