Metadata-Version: 2.1
Name: fake-number-id
Version: 1.0
Summary: generator mobile phone number
License: MIT
Keywords: mobile number generator for all operators in Indonesia
Author: harigro
Author-email: trierbank@gmail.com
Requires-Python: >=3.10,<4.0
Classifier: Development Status :: 5 - Production/Stable
Classifier: Environment :: Console
Classifier: Intended Audience :: Developers
Classifier: License :: OSI Approved :: MIT License
Classifier: Programming Language :: Python
Classifier: Programming Language :: Python :: 3
Classifier: Programming Language :: Python :: 3.10
Classifier: Programming Language :: Python :: 3.11
Classifier: Programming Language :: Python :: 3 :: Only
Classifier: Programming Language :: Python :: 3.7
Classifier: Programming Language :: Python :: 3.8
Classifier: Programming Language :: Python :: 3.9
Classifier: Programming Language :: Python :: Implementation :: CPython
Classifier: Programming Language :: Python :: Implementation :: PyPy
Classifier: Topic :: Software Development :: Libraries :: Python Modules
Classifier: Topic :: Software Development :: Testing
Classifier: Topic :: Utilities
Requires-Dist: faker (>=19.6.2,<20.0.0)
Requires-Dist: phonenumbers (>=8.13.22,<9.0.0)
Project-URL: Documentation, https://github.com/harigro/fake_number_id
Project-URL: Homepage, https://github.com/harigro/fake_number_id
Project-URL: Repository, https://github.com/harigro/fake_number_id
